{"swagger":"2.0","info":{"title":"Page","description":"page","version":""},"host":"localhost:8081","schemes":["http"],"consumes":["application/json","application/xml","application/gob","application/x-gob"],"produces":["application/json","application/xml","application/gob","application/x-gob"],"paths":{"/":{"get":{"tags":["pages"],"summary":"home pages","description":"トップページ","operationId":"pages#home","produces":["text/html; charset=utf-8"],"responses":{"200":{"description":"OK"},"404":{"description":"Not Found"},"500":{"description":"Internal Server Error"}},"schemes":["http"]}},"/complete":{"get":{"tags":["pages"],"summary":"complete pages","description":"完了ページ","operationId":"pages#complete","produces":["text/html; charset=utf-8"],"responses":{"200":{"description":"OK"},"404":{"description":"Not Found"},"500":{"description":"Internal Server Error"}},"schemes":["http"]}}},"responses":{"InternalServerError":{"description":"Internal Server Error"},"NotFound":{"description":"Not Found"}}}